Metadata-Version: 2.1
Name: marginTrading
Version: 0.2
Summary: CryptoCurrency Modules
Home-page: https://github.com/sambiase/pycrypto
Author: Sambiase
Author-email: marsamb@gmail.com
License: MIT License
Platform: UNKNOWN
Classifier: Development Status :: 2 - Pre-Alpha
Classifier: Environment :: Console
Classifier: Intended Audience :: Information Technology
Classifier: License :: OSI Approved :: GNU Affero General Public License v3 or later (AGPLv3+)
Classifier: Operating System :: OS Independent
Classifier: Programming Language :: Python
Classifier: Programming Language :: Python :: 3.9
Classifier: Framework :: Pytest
License-File: LICENSE
